close_encounters/__init__.py
close_encounters/brute_force.py
close_encounters/datasets.py
close_encounters/h3_full_disk.py
close_encounters/h3_half_disk.py
close_encounters/helpers.py
close_encounters/data/__init__.py
close_encounters/data/h3_edgelengths.csv
close_encounters/data/sample_trajectories.parquet
close_encounters-0.1.0.dist-info/licenses/LICENSE
close_encounters-0.1.0.dist-info/METADATA
close_encounters-0.1.0.dist-info/WHEEL
close_encounters-0.1.0.dist-info/top_level.txt
close_encounters-0.1.0.dist-info/RECORD
