Metadata-Version: 2.4
Name: close-encounters
Version: 0.1.0
Summary: A Python module for analyzing close flight encounters using H3.
Author-email: Quinten Goens <quinten.goens@eurocontrol.int>, Esther Calvo Fernandez <esther.calvo-fernandez@eurocontrol.int>
Maintainer-email: Quinten Goens <quinten.goens@eurocontrol.int>
License: MIT
Project-URL: Homepage, https://github.com/euctrl-pru/close-encounters
Project-URL: Repository, https://github.com/euctrl-pru/close-encounters.git
Project-URL: Issues, https://github.com/euctrl-pru/close-encounters/issues
Keywords: aviation,h3,smi,flights,trajectories,fixed-radius-near-neighbours,encounter-detection,close-encounters
Classifier: Development Status :: 3 - Alpha
Classifier: Intended Audience :: Developers
Classifier: Topic :: Scientific/Engineering :: Information Analysis
Classifier: License :: OSI Approved :: MIT License
Classifier: Programming Language :: Python :: 3
Classifier: Programming Language :: Python :: 3.8
Classifier: Programming Language :: Python :: 3.9
Classifier: Programming Language :: Python :: 3.10
Classifier: Programming Language :: Python :: 3.11
Classifier: Programming Language :: Python :: 3.12
Requires-Python: >=3.8
License-File: LICENSE
Requires-Dist: h3==4.2.2
Requires-Dist: tempo==0.12
Requires-Dist: pyarrow
Dynamic: license-file
